gitea_api/__init__.py
gitea_api/api_client.py
gitea_api/configuration.py
gitea_api/rest.py
gitea_api/api/__init__.py
gitea_api/api/admin_api.py
gitea_api/api/issue_api.py
gitea_api/api/miscellaneous_api.py
gitea_api/api/notification_api.py
gitea_api/api/organization_api.py
gitea_api/api/repository_api.py
gitea_api/api/settings_api.py
gitea_api/api/user_api.py
gitea_api/models/__init__.py
gitea_api/models/access_token.py
gitea_api/models/add_collaborator_option.py
gitea_api/models/add_time_option.py
gitea_api/models/annotated_tag.py
gitea_api/models/annotated_tag_object.py
gitea_api/models/api_error.py
gitea_api/models/attachment.py
gitea_api/models/branch.py
gitea_api/models/branch_protection.py
gitea_api/models/combined_status.py
gitea_api/models/comment.py
gitea_api/models/commit.py
gitea_api/models/commit_affected_files.py
gitea_api/models/commit_date_options.py
gitea_api/models/commit_meta.py
gitea_api/models/commit_status.py
gitea_api/models/commit_status_state.py
gitea_api/models/commit_user.py
gitea_api/models/contents_response.py
gitea_api/models/create_access_token_option.py
gitea_api/models/create_branch_protection_option.py
gitea_api/models/create_branch_repo_option.py
gitea_api/models/create_email_option.py
gitea_api/models/create_file_options.py
gitea_api/models/create_fork_option.py
gitea_api/models/create_gpg_key_option.py
gitea_api/models/create_hook_option.py
gitea_api/models/create_hook_option_config.py
gitea_api/models/create_issue_comment_option.py
gitea_api/models/create_issue_option.py
gitea_api/models/create_key_option.py
gitea_api/models/create_label_option.py
gitea_api/models/create_milestone_option.py
gitea_api/models/create_o_auth2_application_options.py
gitea_api/models/create_org_option.py
gitea_api/models/create_pull_request_option.py
gitea_api/models/create_pull_review_comment.py
gitea_api/models/create_pull_review_options.py
gitea_api/models/create_release_option.py
gitea_api/models/create_repo_option.py
gitea_api-1.15.3.post2.dist-info/LICENSE
gitea_api-1.15.3.post2.dist-info/METADATA
gitea_api-1.15.3.post2.dist-info/WHEEL
gitea_api-1.15.3.post2.dist-info/top_level.txt
gitea_api-1.15.3.post2.dist-info/RECORD
