Metadata-Version: 2.1
Name: gitea-api
Version: 1.15.3.post2
Summary: Gitea API.
Home-page: UNKNOWN
Author-email: 
License: UNKNOWN
Keywords: Swagger,Gitea API.
Platform: UNKNOWN
License-File: LICENSE
Requires-Dist: certifi (>=2017.4.17)
Requires-Dist: python-dateutil (>=2.1)
Requires-Dist: six (>=1.10)
Requires-Dist: urllib3 (>=1.23)
